supu/__init__.py
supu/dataframes.py
supu/statistics.py
supu-0.1.0.dist-info/LICENSE
supu-0.1.0.dist-info/WHEEL
supu-0.1.0.dist-info/METADATA
supu-0.1.0.dist-info/RECORD
